jaxboost/__init__.py
jaxboost/_version.py
jaxboost/py.typed
jaxboost/experimental/__init__.py
jaxboost/metric/__init__.py
jaxboost/metric/base.py
jaxboost/metric/bounded.py
jaxboost/metric/classification.py
jaxboost/metric/ordinal.py
jaxboost/metric/regression.py
jaxboost/objective/__init__.py
jaxboost/objective/auto.py
jaxboost/objective/binary.py
jaxboost/objective/multi_output.py
jaxboost/objective/multi_task.py
jaxboost/objective/multiclass.py
jaxboost/objective/ordinal.py
jaxboost/objective/regression.py
jaxboost/objective/survival.py
jaxboost-0.5.0.dist-info/METADATA
jaxboost-0.5.0.dist-info/WHEEL
jaxboost-0.5.0.dist-info/licenses/LICENSE
jaxboost-0.5.0.dist-info/RECORD
