Metadata-Version: 2.4
Name: jaxboost
Version: 0.5.0
Summary: Next-generation differentiable gradient boosting with JAX
Project-URL: Homepage, https://github.com/jxucoder/jaxboost
Project-URL: Documentation, https://jxucoder.github.io/jaxboost/
Project-URL: Repository, https://github.com/jxucoder/jaxboost
Project-URL: Issues, https://github.com/jxucoder/jaxboost/issues
Author-email: J Xu <jxucoder@gmail.com>
License-Expression: Apache-2.0
License-File: LICENSE
Keywords: differentiable-programming,gpu,gradient-boosting,jax,machine-learning,soft-trees
Classifier: Development Status :: 3 - Alpha
Classifier: Intended Audience :: Developers
Classifier: Intended Audience :: Science/Research
Classifier: License :: OSI Approved :: Apache Software License
Classifier: Operating System :: OS Independent
Classifier: Programming Language :: Python :: 3
Classifier: Programming Language :: Python :: 3.10
Classifier: Programming Language :: Python :: 3.11
Classifier: Programming Language :: Python :: 3.12
Classifier: Topic :: Scientific/Engineering :: Artificial Intelligence
Requires-Python: >=3.10
Requires-Dist: chex>=0.1.8
Requires-Dist: jax>=0.4.20
Requires-Dist: jaxlib>=0.4.20
Requires-Dist: optax>=0.1.7
Provides-Extra: benchmark
Requires-Dist: scikit-learn>=1.3.0; extra == 'benchmark'
Requires-Dist: xgboost>=2.0.0; extra == 'benchmark'
Provides-Extra: dev
Requires-Dist: mypy>=1.6.0; extra == 'dev'
Requires-Dist: pytest>=7.4.0; extra == 'dev'
Requires-Dist: ruff>=0.1.0; extra == 'dev'
Provides-Extra: docs
Requires-Dist: mkdocs-material>=9.5.0; extra == 'docs'
Requires-Dist: mkdocs>=1.5.0; extra == 'docs'
Requires-Dist: mkdocstrings[python]>=0.24.0; extra == 'docs'
Provides-Extra: macos
Requires-Dist: jax-metal>=0.1.1; extra == 'macos'
Provides-Extra: ode
Requires-Dist: diffrax>=0.5.0; extra == 'ode'
Provides-Extra: polars
Requires-Dist: polars>=0.19.0; extra == 'polars'
Requires-Dist: pyarrow>=14.0.0; extra == 'polars'
